diagramdigitizer/__init__.py
diagramdigitizer/diagramdigitizer.py
diagramdigitizer/export.py
diagramdigitizer/graphscene.py
diagramdigitizer/utils.py
diagramdigitizer/ui/__init__.py
diagramdigitizer/ui/mainWindow.py
diagramdigitizer/ui/resources_rc.py
diagramdigitizer-1.0.0.dist-info/LICENSE
diagramdigitizer-1.0.0.dist-info/METADATA
diagramdigitizer-1.0.0.dist-info/WHEEL
diagramdigitizer-1.0.0.dist-info/entry_points.txt
diagramdigitizer-1.0.0.dist-info/top_level.txt
diagramdigitizer-1.0.0.dist-info/RECORD
