Metadata-Version: 2.1
Name: diagramdigitizer
Version: 1.0.0
Summary: DiagramDigitizer
Home-page: UNKNOWN
Author: Michael Fischer
Author-email: mfischer.sw@gmail.com
License: UNKNOWN
Project-URL: Source, https://github.com/mfischersw/DiagramDigitizer/
Platform: UNKNOWN
Requires-Python: >=3.6, <4
License-File: LICENSE
